.yaralyzer.example
CHANGELOG.md
LICENSE
yaralyzer/__init__.py
yaralyzer/bytes_match.py
yaralyzer/config.py
yaralyzer/decoding/bytes_decoder.py
yaralyzer/decoding/decoding_attempt.py
yaralyzer/encoding_detection/character_encodings.py
yaralyzer/encoding_detection/encoding_assessment.py
yaralyzer/encoding_detection/encoding_detector.py
yaralyzer/output/console.py
yaralyzer/output/decoding_attempts_table.py
yaralyzer/output/decoding_table_row.py
yaralyzer/output/file_export.py
yaralyzer/output/file_hashes_table.py
yaralyzer/output/regex_match_metrics.py
yaralyzer/output/theme.py
yaralyzer/util/argument_parser.py
yaralyzer/util/classproperty.py
yaralyzer/util/cli_option_validators.py
yaralyzer/util/constants.py
yaralyzer/util/exceptions.py
yaralyzer/util/helpers/bytes_helper.py
yaralyzer/util/helpers/collections_helper.py
yaralyzer/util/helpers/debug_helper.py
yaralyzer/util/helpers/env_helper.py
yaralyzer/util/helpers/file_helper.py
yaralyzer/util/helpers/interaction_helper.py
yaralyzer/util/helpers/rich_helper.py
yaralyzer/util/helpers/shell_helper.py
yaralyzer/util/helpers/string_helper.py
yaralyzer/util/logging.py
yaralyzer/util/timeout.py
yaralyzer/yara/error.py
yaralyzer/yara/yara_match.py
yaralyzer/yara/yara_rule_builder.py
yaralyzer/yaralyzer.py
yaralyzer-1.3.17.dist-info/LICENSE
yaralyzer-1.3.17.dist-info/METADATA
yaralyzer-1.3.17.dist-info/WHEEL
yaralyzer-1.3.17.dist-info/entry_points.txt
yaralyzer-1.3.17.dist-info/RECORD
