Metadata-Version: 2.1
Name: yaralyzer
Version: 1.3.17
Summary: Visualize and force decode YARA and regex matches found in a file or byte stream with colors. Lots of colors.
Home-page: https://github.com/michelcrypt4d4mus/yaralyzer
License: GPL-3.0-or-later
Keywords: ascii art,binary,character encoding,color,cybersecurity,data visualization,decode,DFIR,encoding,infosec,maldoc,malicious,malware,malware analysis,regex,regular expressions,reverse engineering,reversing,security,threat assessment,threat hunting,threat intelligence,threat research,threatintel,visualization,yara
Author: Michel de Cryptadamus
Author-email: michel@cryptadamus.com
Requires-Python: >=3.10,<4.0
Classifier: Development Status :: 5 - Production/Stable
Classifier: Environment :: Console
Classifier: Intended Audience :: Information Technology
Classifier: License :: OSI Approved :: GNU General Public License v3 or later (GPLv3+)
Classifier: Programming Language :: Python
Classifier: Programming Language :: Python :: 3
Classifier: Programming Language :: Python :: 3.10
Classifier: Programming Language :: Python :: 3.11
Classifier: Programming Language :: Python :: 3.12
Classifier: Programming Language :: Python :: 3.13
Classifier: Topic :: Artistic Software
Classifier: Topic :: Scientific/Engineering :: Visualization
Classifier: Topic :: Security
Provides-Extra: img
Requires-Dist: cairosvg (>=2.8.2,<3.0.0) ; extra == "img"
Requires-Dist: chardet (>=5.0.0,<6.0.0)
Requires-Dist: python-dotenv (>=1.1.1,<2.0.0)
Requires-Dist: rich (==14.2.0)
Requires-Dist: rich-argparse-plus (>=0.3.1,<0.4.0)
Requires-Dist: yara-python (>=4.5.4,<5.0.0)
Project-URL: Changelog, https://github.com/michelcrypt4d4mus/yaralyzer/blob/master/CHANGELOG.md
Project-URL: Documentation, https://michelcrypt4d4mus.github.io/yaralyzer/
Project-URL: Repository, https://github.com/michelcrypt4d4mus/yaralyzer
